patreon_dl/__init__.py
patreon_dl/__main__.py
patreon_dl/api.py
patreon_dl/cache.py
patreon_dl/cli.py
patreon_dl/data.py
patreon_dl/decorators.py
patreon_dl/html.py
patreon_dl/http.py
patreon_dl/output.py
patreon_dl-0.0.1.dist-info/LICENSE
patreon_dl-0.0.1.dist-info/METADATA
patreon_dl-0.0.1.dist-info/WHEEL
patreon_dl-0.0.1.dist-info/entry_points.txt
patreon_dl-0.0.1.dist-info/top_level.txt
patreon_dl-0.0.1.dist-info/RECORD
