Metadata-Version: 2.1
Name: patreon-dl
Version: 0.0.1
Summary: Download and sync content from Patreon
Author-email: Ivan Habunek <ivan@habunek.com>
License: GNU GENERAL PUBLIC LICENSE
Project-URL: Homepage, https://git.sr.ht/~ihabunek/patreon-dl
Classifier: Programming Language :: Python :: 3
Classifier: License :: OSI Approved :: GNU General Public License v3 (GPLv3)
Classifier: Operating System :: OS Independent
Classifier: Environment :: Console
Requires-Python: >=3.10
License-File: LICENSE
Requires-Dist: aiohttp
Requires-Dist: click
Requires-Dist: yt-dlp
Provides-Extra: dev
Requires-Dist: build ; extra == 'dev'
Requires-Dist: mypy ; extra == 'dev'
Requires-Dist: pyright ; extra == 'dev'
Requires-Dist: twine ; extra == 'dev'
Requires-Dist: vermin ; extra == 'dev'
